MANIFEST.in
setup.py
cocktail/COPYRIGHT
cocktail/LICENSE
cocktail/__init__.py
cocktail/asynctask.py
cocktail/dateutils.py
cocktail/events.py
cocktail/iteration.py
cocktail/language.py
cocktail/memoryutils.py
cocktail/modeling.py
cocktail/pkgutils.py
cocktail/resourceloader.py
cocktail/sortedcollection.py
cocktail/stringutils.py
cocktail/styled.py
cocktail/typemapping.py
cocktail.egg-info/PKG-INFO
cocktail.egg-info/SOURCES.txt
cocktail.egg-info/dependency_links.txt
cocktail.egg-info/entry_points.txt
cocktail.egg-info/not-zip-safe
cocktail.egg-info/requires.txt
cocktail.egg-info/top_level.txt
cocktail/caching/__init__.py
cocktail/caching/cache.py
cocktail/caching/cacheserializer.py
cocktail/caching/cachestorage.py
cocktail/caching/exceptions.py
cocktail/caching/memorycachestorage.py
cocktail/caching/picklecacheserializer.py
cocktail/caching/restcacheserver.py
cocktail/caching/restcachestorage.py
cocktail/caching/scope.py
cocktail/caching/utils.py
cocktail/controllers/__init__.py
cocktail/controllers/asyncupload.py
cocktail/controllers/autocomplete.py
cocktail/controllers/controller.py
cocktail/controllers/dispatcher.py
cocktail/controllers/displayerror.py
cocktail/controllers/erroremail.py
cocktail/controllers/filepublication.py
cocktail/controllers/fileupload.py
cocktail/controllers/formcontrollermixin.py
cocktail/controllers/formprocessor.py
cocktail/controllers/grouping.py
cocktail/controllers/handlerprofiler.py
cocktail/controllers/imageupload.py
cocktail/controllers/location.py
cocktail/controllers/pagination.py
cocktail/controllers/parameters.py
cocktail/controllers/proxyhandler.py
cocktail/controllers/renderingengines.py
cocktail/controllers/requesthandler.py
cocktail/controllers/requestproperty.py
cocktail/controllers/sessions.py
cocktail/controllers/static.py
cocktail/controllers/uriutils.py
cocktail/controllers/useragentsniffer.py
cocktail/controllers/usercollection.py
cocktail/controllers/userfilter.py
cocktail/controllers/viewstate.py
cocktail/controllers/webservices.py
cocktail/controllers/zodbdebuggertool.py
cocktail/html/AsyncFileUploader.cml
cocktail/html/CollectionView.cml
cocktail/html/ColorDisplay.cml
cocktail/html/CompoundDateSelector.cml
