Metadata-Version: 1.1
Name: cocktail
Version: 1.8.3
Summary: A tasty mix of python web development utilities.
Home-page: UNKNOWN
Author: Whads/Accent SL
Author-email: tech@whads.com
License: UNKNOWN
Platform: UNKNOWN
Classifier: Development Status :: 5 - Production/Stable
Classifier: Intended Audience :: Developers
Classifier: Environment :: Console
Classifier: Environment :: Web Environment
Classifier: Framework :: ZODB
Classifier: License :: OSI Approved :: GNU Affero General Public License v3
Classifier: Operating System :: OS Independent
Classifier: Programming Language :: Python :: 2.7
Classifier: Topic :: Internet :: WWW/HTTP :: Dynamic Content
Classifier: Topic :: Text Processing :: Markup :: HTML
